clevertouch/__init__.py
clevertouch/api.py
clevertouch/devices/__init__.py
clevertouch/devices/const.py
clevertouch/devices/device.py
clevertouch/devices/factory.py
clevertouch/devices/onoff.py
clevertouch/devices/radiator.py
clevertouch/info.py
clevertouch/objects.py
clevertouch/util.py
clevertouch-0.5.0.dist-info/WHEEL
clevertouch-0.5.0.dist-info/METADATA
clevertouch-0.5.0.dist-info/licenses/LICENSE
clevertouch-0.5.0.dist-info/RECORD
