Metadata-Version: 2.1
Name: clevertouch
Version: 0.5.0
Summary: A Python API for interacting with LVI/Purmo Touch E3-connected radiators
License: MIT
Keywords: LVI,home automation,heating
Author-email: hemphen <michael.hemph@gmail.com>
Requires-Python: >=3.8
Classifier: Development Status :: 4 - Beta
Classifier: Intended Audience :: Developers
Classifier: Programming Language :: Python :: 3
Classifier: Topic :: Home Automation
Classifier: Topic :: Software Development :: Libraries :: Python Modules
Requires-Dist: aiohttp>=3.8.1
Project-URL: Source Code, https://github.com/hemphen/clevertouch
